example/__init__.py
example/example_all_processes_itinerum.py
example/example_all_processes_qstarz.py
example/example_all_processes_qstarz_condensed.py
example/example_all_processes_qstarz_known_locations.py
example/example_detect_activities_and_write_csv.py
example/example_detect_complete_days_and_write_csv.py
example/example_detect_trips_and_write_gpkg.py
example/example_detect_trips_and_write_summaries_csv.py
example/example_import_detected_trips_and_map_match.py
example/example_load_trips_and_write_gpkg.py
example/tripkit_config_itinerum.py
example/tripkit_config_qstarz.py
tripkit/__init__.py
tripkit/database.py
tripkit/main.py
tripkit/csvparser/__init__.py
tripkit/csvparser/common.py
tripkit/csvparser/itinerum.py
tripkit/csvparser/qstarz.py
tripkit/io/__init__.py
tripkit/io/csvio.py
tripkit/io/formatters.py
tripkit/io/geojsonio.py
tripkit/io/geopackageio.py
tripkit/io/shapefileio.py
tripkit/io/templates.py
tripkit/models/ActivityLocation.py
tripkit/models/DaySummary.py
tripkit/models/Trip.py
tripkit/models/TripPoint.py
tripkit/models/User.py
tripkit/models/__init__.py
tripkit/process/__init__.py
tripkit/process/activities/__init__.py
tripkit/process/activities/canue/__init__.py
tripkit/process/activities/canue/detect_locations.py
tripkit/process/activities/canue/models.py
tripkit/process/activities/canue/summarize.py
tripkit/process/activities/canue/tally_times.py
tripkit/process/activities/triplab/__init__.py
tripkit/process/activities/triplab/detect.py
tripkit/process/activities/triplab/models.py
tripkit/process/activities/triplab/summarize.py
tripkit/process/canue/__init__.py
tripkit/process/canue/gert_stops.py
tripkit/process/canue/models.py
tripkit/process/canue/preprocess.py
tripkit/process/clustering/__init__.py
tripkit/process/clustering/dbscan_ref.py
tripkit/process/clustering/delta_heading_stdev.py
tripkit/process/clustering/hdbscan_ts.py
tripkit/process/clustering/kmeans.py
tripkit/process/clustering/models.py
itinerum_tripkit-0.0.26.dist-info/LICENSE
itinerum_tripkit-0.0.26.dist-info/METADATA
itinerum_tripkit-0.0.26.dist-info/WHEEL
itinerum_tripkit-0.0.26.dist-info/top_level.txt
itinerum_tripkit-0.0.26.dist-info/RECORD
