Metadata-Version: 2.1
Name: itinerum-tripkit
Version: 0.0.26
Summary: A toolkit for inferencing trips and trip metadata from Itinerum GPS data
Home-page: https://github.com/TRIP-Lab/itinerum-tripkit
Author: Kyle Fitzsimmons
Author-email: kafitz22@gmail.com
License: UNKNOWN
Platform: UNKNOWN
Classifier: Programming Language :: Python :: 3
Classifier: License :: OSI Approved :: GNU General Public License v3 (GPLv3)
Classifier: Operating System :: OS Independent
Requires-Python: >=3.6
License-File: LICENSE
Requires-Dist: fiona (>=1.8.6)
Requires-Dist: geopy (>=1.20.0)
Requires-Dist: networkx (>=2.4)
Requires-Dist: numpy (>=1.17.3)
Requires-Dist: peewee (>=3.10.0)
Requires-Dist: polyline (>=1.4.0)
Requires-Dist: pytz (>=2019.2)
Requires-Dist: requests (>=2.22.0)
Requires-Dist: scipy (>=1.3.1)
Requires-Dist: utm (>=0.5.0)
